{
  "persons": [
    {
      "name": "Arto Hellas",
      "number": "2323",
      "id": 1
    },
    {
      "name": "Ada Lovelace",
      "number": "39-44-5323523",
      "id": 2
    },
    {
      "name": "Dan Abramov",
      "number": "12-43-234345",
      "id": 3
    },
    {
      "name": "Mary Poppendieck",
      "number": "39-23-6423122",
      "id": 4
    },
    {
      "id": 5,
      "name": "ignacio aguirre",
      "number": "7787878"
    },
    {
      "id": 6,
      "name": "pepepepe",
      "number": "2323232"
    },
    {
      "id": 7,
      "name": "sdsdsds",
      "number": "sdsd"
    },
    {
      "id": 8,
      "name": "a",
      "number": "323"
    },
    {
      "id": 9,
      "name": "2222",
      "number": "22"
    },
    {
      "id": 10,
      "name": "232323",
      "number": "sss"
    },
    {
      "id": 11,
      "name": "popo",
      "number": "232323"
    },
    {
      "id": 12,
      "name": "dsdsd",
      "number": "2323"
    },
    {
      "id": 13,
      "name": "pepepe",
      "number": "23"
    },
    {
      "id": 14,
      "name": "sdsdsd",
      "number": "aa"
    },
    {
      "id": 15,
      "name": "sdsd",
      "number": "sdsd"
    },
    {
      "id": 16,
      "name": "sdsds",
      "number": "dd"
    },
    {
      "id": 17,
      "name": "asds",
      "number": "aaa"
    }
  ]
}